CHANGES.rst
CONTRIBUTING.rst
MANIFEST.in
README.rst
setup.cfg
setup.py
docs/LICENSE.GPL
docs/LICENSE.txt
plone/__init__.py
plone.app.ldap.egg-info/PKG-INFO
plone.app.ldap.egg-info/SOURCES.txt
plone.app.ldap.egg-info/dependency_links.txt
plone.app.ldap.egg-info/entry_points.txt
plone.app.ldap.egg-info/namespace_packages.txt
plone.app.ldap.egg-info/not-zip-safe
plone.app.ldap.egg-info/requires.txt
plone.app.ldap.egg-info/top_level.txt
plone/app/__init__.py
plone/app/ldap/__init__.py
plone/app/ldap/config.py
plone/app/ldap/configure.zcml
plone/app/ldap/setuphandlers.py
plone/app/ldap/testing.py
plone/app/ldap/browser/__init__.py
plone/app/ldap/browser/baseform.py
plone/app/ldap/browser/configure.zcml
plone/app/ldap/browser/controlpanel.pt
plone/app/ldap/browser/controlpanel.py
plone/app/ldap/browser/interfaces.py
plone/app/ldap/browser/schema.py
plone/app/ldap/browser/server.py
plone/app/ldap/engine/__init__.py
plone/app/ldap/engine/configure.zcml
plone/app/ldap/engine/interfaces.py
plone/app/ldap/engine/schema.py
plone/app/ldap/engine/server.py
plone/app/ldap/engine/storage.py
plone/app/ldap/engine/vocabulary.py
plone/app/ldap/ploneldap/__init__.py
plone/app/ldap/ploneldap/configure.zcml
plone/app/ldap/ploneldap/exportimport.py
plone/app/ldap/ploneldap/global.py
plone/app/ldap/ploneldap/interfaces.py
plone/app/ldap/ploneldap/schema.py
plone/app/ldap/ploneldap/server.py
plone/app/ldap/ploneldap/util.py
plone/app/ldap/ploneldap/xml/ldap_plugin.xml
plone/app/ldap/profiles/default/componentregistry.xml
plone/app/ldap/profiles/default/controlpanel.xml
plone/app/ldap/profiles/default/metadata.xml
plone/app/ldap/profiles/uninstall/componentregistry.xml
plone/app/ldap/profiles/uninstall/controlpanel.xml
plone/app/ldap/profiles/uninstall/metadata.xml
plone/app/ldap/tests/__init__.py
plone/app/ldap/tests/test_controlpanel.py
plone/app/ldap/tests/test_setup.py