Metadata-Version: 2.1
Name: plone.app.ldap
Version: 1.4.4
Summary: LDAP control panel for Plone 4.2 and higher
Home-page: https://github.com/plone/plone.app.ldap
Author: Wichert Akkerman - Simplon
Author-email: wichert@simplon.biz
Maintainer: Kevin Teague
Maintainer-email: kevin@bud.ca
License: GPL
Keywords: plone ldap
Platform: UNKNOWN
Classifier: Development Status :: 6 - Mature
Classifier: Framework :: Plone
Classifier: Framework :: Plone :: 4.2
Classifier: Framework :: Plone :: 4.3
Classifier: License :: OSI Approved :: GNU General Public License (GPL)
Classifier: Programming Language :: Python
Classifier: Programming Language :: Python :: 2.7
Classifier: Topic :: Software Development :: Libraries :: Python Modules
Classifier: Topic :: System :: Systems Administration :: Authentication/Directory :: LDAP
Provides-Extra: test
